{
    "commands": {},
    "command_classes": [
        {
            "id": 112,
            "values": [
                {
                    "help": "Sets when the LED on the switch is lit.",
                    "label": "LED Light",
                    "index": "3",
                    "max": "2",
                    "min": "0",
                    "size": "1",
                    "type": "list",
                    "value": "0",
                    "items": [
                        {
                            "label": "LED on when light off",
                            "value": "0"
                        },
                        {
                            "label": "LED on when light on",
                            "value": "1"
                        },
                        {
                            "label": "LED always off",
                            "value": "2"
                        }
                    ]
                },
                {
                    "help": "Change the top of the switch to OFF and the bottom of the switch to ON, if the switch was installed upside down.",
                    "label": "Invert Switch",
                    "index": "4",
                    "max": "1",
                    "min": "0",
                    "size": "1",
                    "type": "list",
                    "value": "0",
                    "items": [
                        {
                            "label": "No",
                            "value": "0"
                        },
                        {
                            "label": "Yes",
                            "value": "1"
                        }
                    ]
                },
                {
                    "help": "Indicates how many levels the dimmer will change for each dimming step.",
                    "label": "Z-Wave Command Dim Step",
                    "index": "7",
                    "max": "99",
                    "min": "1",
                    "type": "byte",
                    "units": "",
                    "value": "1",
                    "items": []
                },
                {
                    "help": "This value indicates in 10 millisecond resolution, how often the dim level will change. For example, if you set this parameter to 1, then every 10ms the dim level will change. If you set it to 255, then every 2.55 seconds the dim level will change.",
                    "label": "Z-Wave Command Dim Rate",
                    "index": "8",
                    "max": "255",
                    "min": "1",
                    "type": "byte",
                    "units": "x 10 milliseconds",
                    "value": "3",
                    "items": []
                },
                {
                    "help": "Indicates how many levels the dimmer will change for each dimming step.",
                    "label": "Local Control Dim Step",
                    "index": "9",
                    "max": "99",
                    "min": "1",
                    "type": "byte",
                    "units": "",
                    "value": "1",
                    "items": []
                },
                {
                    "help": "This value indicates in 10 millisecond resolution, how often the dim level will change. For example, if you set this parameter to 1, then every 10ms the dim level will change. If you set it to 255, then every 2.55 seconds the dim level will change.",
                    "label": "Local Control Dim Rate",
                    "index": "10",
                    "max": "255",
                    "min": "1",
                    "type": "byte",
                    "units": "x 10 milliseconds",
                    "value": "3",
                    "items": []
                },
                {
                    "help": "Indicates how many levels the dimmer will change for each dimming step.",
                    "label": "ALL ON/ALL OFF Dim Step",
                    "index": "11",
                    "max": "99",
                    "min": "1",
                    "type": "byte",
                    "units": "",
                    "value": "1",
                    "items": []
                },
                {
                    "help": "This value indicates in 10 millisecond resolution, how often the dim level will change. For example, if you set this parameter to 1, then every 10ms the dim level will change. If you set it to 255, then every 2.55 seconds the dim level will change.",
                    "label": "ALL ON/ALL OFF Dim Rate",
                    "index": "12",
                    "max": "255",
                    "min": "1",
                    "type": "byte",
                    "units": "x 10 milliseconds",
                    "value": "3",
                    "items": []
                }
            ]
        }
    ],
    "configurations": [],
    "meta": {
        "display": {
            "manufacturer": "GE",
            "product": "12730 Fan Control Switch"
        }
    },
    "manufacturerId": 99,
    "productId": 12340,
    "productTypeId": 18756
}